daft_meizter_ingestion/__init__.py
daft_meizter_ingestion/daft_meizter_ingestion.py
daft_meizter_ingestion-0.0.4.dist-info/LICENSE
daft_meizter_ingestion-0.0.4.dist-info/METADATA
daft_meizter_ingestion-0.0.4.dist-info/WHEEL
daft_meizter_ingestion-0.0.4.dist-info/top_level.txt
daft_meizter_ingestion-0.0.4.dist-info/RECORD
