Metadata-Version: 2.1
Name: daft_meizter_ingestion
Version: 0.0.4
Summary: lakehouse with daft
Author: Douglas B. Martins
Author-email: douglas@meizter.com
Classifier: Programming Language :: Python :: 3
Classifier: License :: OSI Approved :: MIT License
Classifier: Operating System :: OS Independent
Requires-Python: >=3.6
License-File: LICENSE
Requires-Dist: aiobotocore==2.15.2
Requires-Dist: aiohappyeyeballs==2.4.4
Requires-Dist: aiohttp==3.11.10
Requires-Dist: aioitertools==0.12.0
Requires-Dist: aiosignal==1.3.1
Requires-Dist: annotated-types==0.7.0
Requires-Dist: asttokens==3.0.0
Requires-Dist: attrs==24.2.0
Requires-Dist: boto3==1.35.36
Requires-Dist: botocore==1.35.36
Requires-Dist: cachetools==5.5.0
Requires-Dist: certifi==2024.8.30
Requires-Dist: charset-normalizer==3.4.0
Requires-Dist: click==8.1.7
Requires-Dist: colorama==0.4.6
Requires-Dist: comm==0.2.2
Requires-Dist: debugpy==1.8.9
Requires-Dist: decorator==5.1.1
Requires-Dist: executing==2.1.0
Requires-Dist: frozenlist==1.5.0
Requires-Dist: fsspec==2023.12.2
Requires-Dist: getdaft==0.3.15
Requires-Dist: idna==3.10
Requires-Dist: ipykernel==6.29.5
Requires-Dist: ipython==8.30.0
Requires-Dist: jedi==0.19.2
Requires-Dist: jmespath==1.0.1
Requires-Dist: jupyter_client==8.6.3
Requires-Dist: jupyter_core==5.7.2
Requires-Dist: markdown-it-py==3.0.0
Requires-Dist: matplotlib-inline==0.1.7
Requires-Dist: mdurl==0.1.2
Requires-Dist: mmh3==5.0.1
Requires-Dist: multidict==6.1.0
Requires-Dist: nest-asyncio==1.6.0
Requires-Dist: numpy==2.2.0
Requires-Dist: packaging==24.2
Requires-Dist: pandas==2.2.3
Requires-Dist: parso==0.8.4
Requires-Dist: platformdirs==4.3.6
Requires-Dist: prompt_toolkit==3.0.48
Requires-Dist: propcache==0.2.1
Requires-Dist: psutil==6.1.0
Requires-Dist: pure_eval==0.2.3
Requires-Dist: pyarrow==18.1.0
Requires-Dist: pydantic==2.10.3
Requires-Dist: pydantic_core==2.27.1
Requires-Dist: Pygments==2.18.0
Requires-Dist: pyiceberg==0.8.0
Requires-Dist: pyparsing==3.2.0
Requires-Dist: python-dateutil==2.9.0.post0
Requires-Dist: python-dotenv==1.0.1
Requires-Dist: pytz==2024.2
Requires-Dist: pywin32==308
Requires-Dist: pyzmq==26.2.0
Requires-Dist: requests==2.32.3
Requires-Dist: rich==13.9.4
Requires-Dist: s3fs==2023.12.2
Requires-Dist: s3transfer==0.10.4
Requires-Dist: setuptools==75.6.0
Requires-Dist: six==1.17.0
Requires-Dist: sortedcontainers==2.4.0
Requires-Dist: stack-data==0.6.3
Requires-Dist: strictyaml==1.7.3
Requires-Dist: tenacity==9.0.0
Requires-Dist: tornado==6.4.2
Requires-Dist: tqdm==4.67.1
Requires-Dist: traitlets==5.14.3
Requires-Dist: typing_extensions==4.12.2
Requires-Dist: tzdata==2024.2
Requires-Dist: urllib3==2.2.3
Requires-Dist: wcwidth==0.2.13
Requires-Dist: wheel==0.45.1
Requires-Dist: wrapt==1.17.0
Requires-Dist: yarl==1.18.3
